pysharkfeat/__init__.py
pysharkfeat/feat.py
pysharkfeat/featextractor.py
pysharkfeat/logger.py
pysharkfeat/stream.py
pysharkfeat/util.py
pysharkfeat-0.1.dist-info/LICENSE
pysharkfeat-0.1.dist-info/METADATA
pysharkfeat-0.1.dist-info/WHEEL
pysharkfeat-0.1.dist-info/top_level.txt
pysharkfeat-0.1.dist-info/RECORD
