Metadata-Version: 2.1
Name: pysharkfeat
Version: 0.1
Summary: an open source TLS encrypted traffic feature extraction tool from pcaps
Home-page: https://github.com/zliucd/pysharkfeat
Author: Zhi Liu
Author-email: cowliucd@gmail.com
License: UNKNOWN
Platform: UNKNOWN
Classifier: Programming Language :: Python :: 3
Classifier: Topic :: Scientific/Engineering
Classifier: License :: OSI Approved :: GNU General Public License v3 (GPLv3)
Classifier: Operating System :: OS Independent
License-File: LICENSE
Requires-Dist: numpy (>=1.18)
